merge/__init__.py
merge/client.py
merge/core/__init__.py
merge/core/api_error.py
merge/core/client_wrapper.py
merge/core/datetime_utils.py
merge/core/jsonable_encoder.py
merge/core/remove_none_from_dict.py
merge/environment.py
merge/py.typed
merge/resources/__init__.py
merge/resources/accounting/__init__.py
merge/resources/accounting/client.py
merge/resources/accounting/resources/__init__.py
merge/resources/accounting/resources/account_details/__init__.py
merge/resources/accounting/resources/account_details/client.py
merge/resources/accounting/resources/account_token/__init__.py
merge/resources/accounting/resources/account_token/client.py
merge/resources/accounting/resources/accounts/__init__.py
merge/resources/accounting/resources/accounts/client.py
merge/resources/accounting/resources/addresses/__init__.py
merge/resources/accounting/resources/addresses/client.py
merge/resources/accounting/resources/async_passthrough/__init__.py
merge/resources/accounting/resources/async_passthrough/client.py
merge/resources/accounting/resources/attachments/__init__.py
merge/resources/accounting/resources/attachments/client.py
merge/resources/accounting/resources/available_actions/__init__.py
merge/resources/accounting/resources/available_actions/client.py
merge/resources/accounting/resources/balance_sheets/__init__.py
merge/resources/accounting/resources/balance_sheets/client.py
merge/resources/accounting/resources/cash_flow_statements/__init__.py
merge/resources/accounting/resources/cash_flow_statements/client.py
merge/resources/accounting/resources/company_info/__init__.py
merge/resources/accounting/resources/company_info/client.py
merge/resources/accounting/resources/contacts/__init__.py
merge/resources/accounting/resources/contacts/client.py
merge/resources/accounting/resources/credit_notes/__init__.py
merge/resources/accounting/resources/credit_notes/client.py
merge/resources/accounting/resources/delete_account/__init__.py
fern_merge-0.2.9.dist-info/METADATA
fern_merge-0.2.9.dist-info/WHEEL
fern_merge-0.2.9.dist-info/RECORD
